digiplot/__init__.py
digiplot/_version.py
digiplot/fix_distortion.py
digiplot/plot_area.py
digiplot/realign_Dialog.py
digiplot/sample_img.py
digiplot/tk_digiplot.py
digiplot/examples/Em_original_4Point.jpg
digiplot/examples/Tank_ExpEff_3Point.jpg
digiplot/examples/chk_rot_fix_img.py
digiplot/examples/example_1.py
digiplot/examples/fix_distortion.py
digiplot/examples/fix_rot_img.py
digiplot/examples/log_log_plot.jpg
digiplot/examples/make_rot_img.py
digiplot/examples/rot_poly_m3.jpg
digiplot/examples/rot_poly_p3.jpg
digiplot/examples/sample_poly.png
digiplot/examples/sample_poly.py
digiplot/fonts/FreeSerifBoldItalic.ttf
digiplot/tests/__init__.py
digiplot/tests/test_plot_area.py
digiplot-0.1.4.dist-info/METADATA
digiplot-0.1.4.dist-info/RECORD
digiplot-0.1.4.dist-info/WHEEL
digiplot-0.1.4.dist-info/entry_points.txt
digiplot-0.1.4.dist-info/top_level.txt
